pyodys/__init__.py
pyodys/__main__.py
pyodys/ode/ODEProblem.py
pyodys/ode/__init__.py
pyodys/schemes/__init__.py
pyodys/schemes/scheme.py
pyodys/schemes/bdf/BDFScheme.py
pyodys/schemes/bdf/__init__.py
pyodys/schemes/rk/RKScheme.py
pyodys/schemes/rk/__init__.py
pyodys/schemes/rk/butcher_tableaus_data/__init__.py
pyodys/schemes/rk/butcher_tableaus_data/available_butcher_table_data_to_json.py
pyodys/solvers/BDFSolver.py
pyodys/solvers/PyodysSolver.py
pyodys/solvers/RKSolver.py
pyodys/solvers/SolverBase.py
pyodys/solvers/__init__.py
pyodys/utils/__init__.py
pyodys/utils/command_line_arguments_parser.py
pyodys/utils/interpolation.py
pyodys/utils/pyodys_utils.py
pyodys-0.1.1.dist-info/licenses/LICENSE
pyodys-0.1.1.dist-info/METADATA
pyodys-0.1.1.dist-info/WHEEL
pyodys-0.1.1.dist-info/top_level.txt
pyodys-0.1.1.dist-info/RECORD
