Metadata-Version: 2.4
Name: pyodys
Version: 0.1.1
Summary: This is a robust and flexible Python package for solving ordinary differential equations (ODEs). The solver is built to handle both explicit and implicit Runge–Kutta methods using a powerful Butcher tableau approach, and it includes a numerical Jacobian for convenience.
Author-email: Ismaël Tchinda Ngueyong <pyodyscontact@gmail.com>
License: MIT License
Project-URL: Homepage, https://github.com/itchinda/pyodys-project/
License-File: LICENSE
Requires-Dist: numpy
Requires-Dist: scipy
Dynamic: license-file
